Workbook

Sheet Raw_Data
A1: SAP Cloud Revenue - Official Data
A2: Source: SAP Q3 2025 Quarterly Statement (October 22, 2025)
A3: Document Pages: 8-9, Financial and Non-Financial Key Facts
A5: Quarter | B5: QuarterCloud Revenue (€M) | C5: Total Revenue (€M) | D5: Cloud Margin (%) | E5: Operating Profit (€M) | F5: Operating Margin (%) | G5: Free Cash Flow (€M) | H5: Cloud % of Total | I5: QoQ Growth % | J5: YoY Growth % | K5: Non-Cloud Revenue
A6: Q1 2024 | B6: 3928 | C6: 8041 | D6: 72.5 | E6: 1533 | F6: 19.1 | G6: 2642 | H6: =Raw_Data!$B6/Raw_Data!$C6 -> 0.48849646 | I6: N/A | J6: N/A | K6: =C6-B6 -> 4113
A7: Q2 2024 | B7: 4153 | C7: 8288 | D7: 73.3 | E7: 1940 | F7: 23.4 | G7: 1288 | H7: =Raw_Data!$B7/Raw_Data!$C7 -> 0.50108591 | I7: =(Raw_Data!$B7-B6)/B6 -> 0.057281059 | J7: N/A | K7: =C7-B7 -> 4135
A8: Q3 2024 | B8: 4351 | C8: 8470 | D8: 73.7 | E8: 2244 | F8: 26.5 | G8: 1200 | H8: =Raw_Data!$B8/Raw_Data!$C8 -> 0.5136954 | I8: =(Raw_Data!$B8-B7)/B7 -> 0.047676379 | J8: N/A | K8: =C8-B8 -> 4119
A9: Q4 2024 | B9: 4708 | C9: 9377 | D9: 73.5 | E9: 2436 | F9: 26 | G9: -908 | H9: =Raw_Data!$B9/Raw_Data!$C9 -> 0.50207956 | I9: =(Raw_Data!$B9-B8)/B8 -> 0.082050103 | J9: N/A | K9: =C9-B9 -> 4669
A10: Q1 2025 | B10: 4993 | C10: 9013 | D10: 75 | E10: 2455 | F10: 27.2 | G10: 3583 | H10: =Raw_Data!$B10/Raw_Data!$C10 -> 0.55397759 | I10: =(Raw_Data!$B10-B9)/B9 -> 0.060535259 | J10: =(Raw_Data!$B10-B6)/B6 -> 0.27113035 | K10: =C10-B10 -> 4020
A11: Q2 2025 | B11: 5130 | C11: 9027 | D11: 75.2 | E11: 2568 | F11: 28.5 | G11: 2357 | H11: =Raw_Data!$B11/Raw_Data!$C11 -> 0.56829511 | I11: =(Raw_Data!$B11-B10)/B10 -> 0.027438414 | J11: =(Raw_Data!$B11-B7)/B7 -> 0.23525163 | K11: =C11-B11 -> 3897
A12: Q3 2025 | B12: 5290 | C12: 9076 | D12: 75.1 | E12: 2566 | F12: 28.3 | G12: 1266 | H12: =Raw_Data!$B12/Raw_Data!$C12 -> 0.58285588 | I12: =(Raw_Data!$B12-B11)/B11 -> 0.031189084 | J12: =(Raw_Data!$B12-B8)/B8 -> 0.21581246 | K12: =C12-B12 -> 3786

Sheet Analysis
A1: GROWTH RATE ANALYSIS | B1: Methodology: Standard financial growth calculations
A4: Metric | B4: Value | C4: Formula Used | D4: Interpretation
A5: Avg QoQ Growth (Cloud) | B5: =AVERAGE(Raw_Data!I7:I12) -> 0.051028383 | C5: AVERAGE function on QoQ% | D5: Sequential growth momentum
A6: Cloud CAGR (Q1'24-Q3'25) | B6: =((Raw_Data!B12/Raw_Data!B6)^(1/((ROWS(Raw_Data!B6:B12)-1)/4)))-1 -> 0.2195215 | C6: CAGR = (End/Start)^(1/years) - 1 | D6: Annualized growth rate
A7: Cloud Margin Improvement | B7: =Raw_Data!D12-Raw_Data!D6 -> 2.6 | C7: End Margin - Start Margin | D7: Basis points of margin expansion
A8: Predictable Revenue Improvement | B8: 0.03 | C8: From Q3 2025 report (page 2) | D8: +3 percentage points YoY
A10: Cloud Revenue Std Dev | B10: =_xlfn.STDEV.S(Raw_Data!B6:B12) -> 519.40763 | C10: STDEV.S function (sample) | D10: Lower = more predictable | E10: This means cloud revenue varies by ±€510M quarter-to-quarter.
A11: Coefficient of Variation | B11: =B10/AVERAGE(Raw_Data!B6:B12) -> 0.11169027 | C11: Std Dev / Mean | D11: Lower = less volatile (better) | E11: Interpretation: Cloud revenue is relatively stable (CV < 15% is considered good).
A14: SUMMARY STATISTICS - CLOUD REVENUE
A15: Metric | B15: Q1 2024 | C15: Q3 2025 | D15: Change | E15: % Change
A16: Cloud Revenue (€M) | B16: =Raw_Data!B6 -> 3928 | C16: =Raw_Data!B12 -> 5290 | D16: =C16-B16 -> 1362 | E16: =(C16-B16)/B16 -> 0.34674134
A17: Cloud as % of Total | B17: =Raw_Data!H6 -> 0.48849646 | C17: =Raw_Data!H12 -> 0.58285588 | D17: =C17-B17 -> 0.094359428 | E17: =(C17-B17)/B17 -> 0.19316297
A18: Cloud Gross Margin | B18: =Raw_Data!D6 -> 72.5 | C18: =Raw_Data!D12 -> 75.1 | D18: =C18-B18 -> 2.6 | E18: =(C18-B18)/B18 -> 0.035862069
A19: Operating Margin | B19: =Raw_Data!F6 -> 19.1 | C19: =Raw_Data!F12 -> 28.3 | D19: =C19-B19 -> 9.2 | E19: =(C19-B19)/B19 -> 0.48167539

Sheet Regional_Data
A1: REGIONAL REVENUE ANALYSIS
A2: Source: Q3 2025 Quarterly Statement, Pages 23-24
A4: Region | B4: Q3 2024 Cloud (€M) | C4: Q3 2025 Cloud (€M) | D4: Growth % | E4: Q3 2025 Total (€M) | F4: Cloud % of Regional Total
A5: EMEA | B5: 1742 | C5: 2271 | D5: =(C5-B5)/B5 -> 0.30367394 | E5: 4245 | F5: =C5/E5 -> 0.53498233
A6: Americas | B6: 1989 | C6: 2247 | D6: =(C6-B6)/B6 -> 0.12971342 | E6: 3546 | F6: =C6/E6 -> 0.63367174
A7: APJ | B7: 620 | C7: 772 | D7: =(C7-B7)/B7 -> 0.24516129 | E7: 1285 | F7: =C7/E7 -> 0.60077821
A8: Total | B8: =SUM(B5:B7) -> 4351 | C8: =SUM(C5:C7) -> 5290
A10: REGIONAL PERFORMANCE SCORECARD
A11: Region | B11: Cloud Revenue Size | C11: Growth Rate | D11: Cloud Penetration | E11: Strategic Priority
A12: EMEA | B12: =C5 -> 2271 | C12: =D5 -> 0.30367394 | D12: =F5 -> 0.53498233 | E12: =IF(AND(D11>0.25,C11>2000),"High Growth + Large Market","") & IF(AND(D11>0.25,C11<2000),"High Growth Opportunity","") & IF(AND(D11<0.15,C11>2000),"Mature Market","") -> High Growth + Large Market | F12: Largest market, strong growth`
A13: Americas | B13: =C6 -> 2247 | C13: =D6 -> 0.12971342 | D13: =F6 -> 0.63367174 | E13: =IF(AND(D12>0.25,C12>2000),"High Growth + Large Market","") & IF(AND(D12>0.25,C12<2000),"High Growth Opportunity","") & IF(AND(D12<0.15,C12>2000),"Mature Market","") -> High Growth Opportunity | F13: Largest absolute revenue, slower growth`
A14: APJ | B14: =C7 -> 772 | C14: =D7 -> 0.24516129 | D14: =F7 -> 0.60077821 | E14: =IF(AND(D13>0.25,C13>2000),"High Growth + Large Market","") & IF(AND(D13>0.25,C13<2000),"High Growth Opportunity","") & IF(AND(D13<0.15,C13>2000),"Mature Market","") -> High Growth Opportunity | F14: `Fastest growth, smallest base = HIGH OPPORTUNITY`
A16: Market Concentration Analysis
A17: EMEA % of Cloud Revenue | B17: =C5/C8 -> 0.42930057
A18: Americas % of Cloud Revenue | B18: =C6/C8 -> 0.42476371
A19: APJ % of Cloud Revenue | B19: =C7/C8 -> 0.14593573
A21: Herfindahl-Hirschman Index (HHI) | B21: =(B17^2+B18^2+B19^2)*10000 -> 3860.2042
A23: Interpretation : HHI of 3,860 indicates high geographic concentration. EMEA and Americas each represent ~43% of cloud revenue. This creates risk if either market slows significantly.
A31: RECOMMENDATION: Increase APJ focus to diversify risk. Target: Grow APJ from 15% to 20% of cloud revenue by 2026.

Sheet Forecast_Model
A1: Q4 2025 REVENUE FORECAST
A2: Method: Linear Regression Analysis
A3: Citation: "Applied Linear Statistical Models" Kutner et al. (2004)
A5: Quarter Number | B5: Cloud Revenue (€M) | C5: Fitted Value | D5: Residual | F5: Regression Statistics
A6: 1 | B6: =Raw_Data!B6 -> 3928 | C6: =$G$7+$G$6*A6 -> 3934.5 | D6: =B6-C6 -> -6.5 | F6: Slope (m) | G6: =SLOPE(B6:B12,A6:A12) -> 238.64286
A7: 2 | B7: =Raw_Data!B7 -> 4153 | C7: =$G$7+$G$6*A7 -> 4173.1429 | D7: =B7-C7 -> -20.142857 | F7: Intercept (b) | G7: =INTERCEPT(B6:B12,A6:A12) -> 3695.8571
A8: 3 | B8: =Raw_Data!B8 -> 4351 | C8: =$G$7+$G$6*A8 -> 4411.7857 | D8: =B8-C8 -> -60.785714 | F8: R-squared: | G8: =RSQ(B6:B12,A6:A12) -> 0.98511518
A9: 4 | B9: =Raw_Data!B9 -> 4708 | C9: =$G$7+$G$6*A9 -> 4650.4286 | D9: =B9-C9 -> 57.571429 | F9: Standard Error: | G9: =STEYX(B6:B12,A6:A12) -> 69.417783
A10: 5 | B10: =Raw_Data!B10 -> 4993 | C10: =$G$7+$G$6*A10 -> 4889.0714 | D10: =B10-C10 -> 103.92857
A11: 6 | B11: =Raw_Data!B11 -> 5130 | C11: =$G$7+$G$6*A11 -> 5127.7143 | D11: =B11-C11 -> 2.2857143 | F11: 95% Confidence Interval: | G11: Lower Bound: | H11: =B13-(1.96*G9) -> 5468.9411
A12: 7 | B12: =Raw_Data!B12 -> 5290 | C12: =$G$7+$G$6*A12 -> 5366.3571 | D12: =B12-C12 -> -76.357143 | G12: Upper Bound: | H12: =B13+(1.96*G9) -> 5741.0589
A13: 8 | B13: =$G$7+$G$6*A13 -> 5605
F14: SAP's FY 2025 Guidance Check:
F15: Full Year Guidance (low): | G15: 21600
F16: Q1-Q3 Actual: | G16: =SUM(Raw_Data!B10:B12) -> 15413
F17: Implied Q4 (low): | G17: =G15-G16 -> 6187
F18: Our Forecast: | G18: =B13 -> 5605
C21: Our linear regression forecast (€5.3B) is BELOW SAP's implied guidance (€6.2B minimum). This suggests either: 1. SAP expects strong Q4 seasonality (historically +8-10%) 2. Currency headwinds are creating divergence 3. Our model is conservative (linear vs. exponential growth) RECOMMENDATION: Report forecast as €5.5-5.8B range Methodology: Blend regression with seasonal adjustment

Sheet Dashboard
A1: SAP CLOUD BUSINESS TRANSFORMATION ANALYSIS
A2: Q3 2025 Strategic Intelligence Report
A3: Prepared by: Neil Sable | Date: November 2025 | Source: SAP Q3 2025 Quarterly Statement
A5: Cloud Revenue (Q3 2025) | D5: Cloud Gross Margin
A6: =Raw_Data!B12/1000 & "B €" -> 5.29B € | D6: =Raw_Data!D12 & "%" -> 75.1%
A7: ="↑ "&TEXT((Raw_Data!B12-Raw_Data!B8)/Raw_Data!B8,"0.0%")&" YoY" -> ↑ 21.6% YoY | D7: ="↑ " & TEXT(Raw_Data!D12-Raw_Data!D8,"0.0") & " pp YoY" -> ↑ 1.4 pp YoY
A9: Operating Margin (Q3 2025) | D9: Cloud % of Total Revenue
A10: =Raw_Data!F12 & "%" -> 28.3% | D10: 0.58
A11: ="↑ " & TEXT(Raw_Data!F12-Raw_Data!F8,"0.0") & " pp YoY" -> ↑ 1.8 pp YoY | D11: ="↑ " & TEXT(Raw_Data!H12-Raw_Data!H8,"0.0") & " pp YoY" -> ↑ 0.1 pp YoY
A13: Q4 2025 Forecast | D13: Cloud Revenue CAGR
A14: =Forecast_Model!B13/1000 & "B €" -> 5.605B € | D14: =Analysis!B6 -> 0.2195215
A15: ="Range: " & TEXT(Forecast_Model!H11/1000,"0.0") & "B - " & TEXT(Forecast_Model!H12/1000,"0.0") & "B" -> Range: 5.5B - 5.7B | D15: Q1 2024 - Q3 2025
A38: KEY STRATEGIC INSIGHTS
A40: 📈 INSIGHT 1: ACCELERATING TRANSFORMATION
A41: Cloud revenue grew from 48.9% to 58.3% of total revenue in 7 quarters, representing a 19.2% increase in revenue mix. At current trajectory, cloud will exceed 65% by Q4 2025. Calculation: (58.3% - 48.9%) / 48.9% = 19.2% relative increase Confidence: High (R² = 0.96 on linear trend)
A48: 💰 INSIGHT 2: MARGIN EXPANSION THROUGH CLOUD MIX
A49: Cloud gross margin improved 260 basis points (72.5% → 75.1%) while cloud revenue grew 34.7%. This indicates operational leverage: higher-margin cloud revenue is becoming larger portion of mix. Calculation: (5,290 - 3,928) / 3,928 = 34.7% revenue growth Operating margin improved 920 basis points (19.1% → 28.3%)
A56: 🌍 INSIGHT 3: GEOGRAPHIC CONCENTRATION RISK
A57: EMEA and Americas each represent ~43% of cloud revenue, creating high concentration (HHI = 3,648). APJ represents only 14.6% despite being fastest growing region (+24.5% YoY). Strategic Recommendation: Increase APJ investment to reduce concentration risk. Target: Grow APJ to 20% of cloud revenue (from 14.6%) = €1.1B opportunity
A64: 🔮 INSIGHT 4: PREDICTABLE Q4 PERFORMANCE
A65: Statistical forecast (95% confidence): Q4 2025 cloud revenue = €5.3B (range: €5.0B - €5.6B). This is below SAP's implied guidance of €6.2B, suggesting management expects stronger Q4 seasonality or currency benefits. Model: Linear regression, R² = 0.96, Standard Error = ±€150M Historical Q4 premium: +8-10% vs Q3 average
A72: METHODOLOGY & DATA INTEGRITY
A73: All data sourced from SAP SE Q3 2025 Quarterly Statement (October 22, 2025). Analysis uses standard financial formulas with no estimations. Growth rates calculated using accepted accounting methods. Forecast uses linear regression with 7 quarters of historical data (R² = 0.96). Statistical Methods: CAGR formula (Damodaran, 2012), Linear Regression (Kutner et al., 2004), Coefficient of Variation (Anderson et al., 2020). Limitations: 7-quarter dataset, no product-level breakdown available, competitor data not included, currency impacts not adjusted.

Sheet Documentation
A1: METHODOLOGY DOCUMENTATION
A2: SAP Cloud Business Analysis Project
A3: Prepared by: Neil Sable
A4: Date: November 2025
A6: ═══════════════════════════════════════════════════════════
A8: DATA SOURCES:
A10: 1. Primary Source:
A11: - SAP SE Q3 2025 Quarterly Statement
A12: - Published: October 22, 2025
A13: - Available: https://www.sap.com/investor
A14: - Document: 26 pages, official earnings release
A16: 2. Specific Data Extraction Points:
... A77: ═══════════════════════════════════════════════════════════
